{
  "CodeKitInfo" : "This is a CodeKit project configuration file. It is designed to sync project settings across multiple machines. Modifying the contents of this file can be a poor life decision if you don't know what you're doing. This file is not useful unless accompanied by the project that created it in CodeKit. For more information, see: http:\/\/incident57.com\/codekit",
  "creatorBuild" : "8403",
  "files" : {
    "\/less\/includes\/bootstrap\/accordion.less" : {
      "ieCompatibility" : 1,
      "inputAbbreviatedPath" : "\/less\/includes\/bootstrap\/accordion.less",
      "outputAbbreviatedPath" : "\/less\/includes\/css\/accordion.css",
      "outputPathIsSetByUser" : 0,
      "strictUnits" : 0,
      "relativeURLS" : 0,
      "ignore" : 1,
      "strictImports" : 0,
      "ignoreWasSetByUser" : 0,
      "shouldRunBless" : 0,
      "hidden" : 0,
      "strictMath" : 0,
      "outputStyle" : 0,
      "fileType" : 1,
      "debugStyle" : 0
    },
    "\/less\/includes\/bootstrap\/responsive-navbar.less" : {
      "ieCompatibility" : 1,
      "inputAbbreviatedPath" : "\/less\/includes\/bootstrap\/responsive-navbar.less",
      "outputAbbreviatedPath" : "\/less\/includes\/css\/responsive-navbar.css",
      "outputPathIsSetByUser" : 0,
      "strictUnits" : 0,
      "relativeURLS" : 0,
      "ignore" : 1,
      "strictImports" : 0,
      "ignoreWasSetByUser" : 0,
      "shouldRunBless" : 0,
      "hidden" : 0,
      "strictMath" : 0,
      "outputStyle" : 0,
      "fileType" : 1,
      "debugStyle" : 0
    },
    "\/less\/includes\/bootstrap\/tests\/css-tests.html" : {
      "ignoreWasSetByUser" : 0,
      "ignore" : 0,
      "hidden" : 0,
      "outputPathIsSetByUser" : 0,
      "inputAbbreviatedPath" : "\/less\/includes\/bootstrap\/tests\/css-tests.html",
      "outputAbbreviatedPath" : "No Output Path",
      "fileType" : 2048
    },
    "\/less\/includes\/bootstrap\/tests\/forms.html" : {
      "ignoreWasSetByUser" : 0,
      "ignore" : 0,
      "hidden" : 0,
      "outputPathIsSetByUser" : 0,
      "inputAbbreviatedPath" : "\/less\/includes\/bootstrap\/tests\/forms.html",
      "outputAbbreviatedPath" : "No Output Path",
      "fileType" : 2048
    },
    "\/img\/monster\/body.png" : {
      "ignoreWasSetByUser" : 0,
      "ignore" : 0,
      "hidden" : 0,
      "outputPathIsSetByUser" : 0,
      "inputAbbreviatedPath" : "\/img\/monster\/body.png",
      "processed" : 1,
      "outputAbbreviatedPath" : "\/img\/monster\/body.png",
      "initialSize" : 13948,
      "fileType" : 8192
    },
    "\/less\/includes\/bootstrap\/alerts.less" : {
      "ieCompatibility" : 1,
      "inputAbbreviatedPath" : "\/less\/includes\/bootstrap\/alerts.less",
      "outputAbbreviatedPath" : "\/less\/includes\/css\/alerts.css",
      "outputPathIsSetByUser" : 0,
      "strictUnits" : 0,
      "relativeURLS" : 0,
      "ignore" : 1,
      "strictImports" : 0,
      "ignoreWasSetByUser" : 0,
      "shouldRunBless" : 0,
      "hidden" : 0,
      "strictMath" : 0,
      "outputStyle" : 0,
      "fileType" : 1,
      "debugStyle" : 0
    },
    "\/img\/monster\/right-arm.png" : {
      "ignoreWasSetByUser" : 0,
      "ignore" : 0,
      "hidden" : 0,
      "outputPathIsSetByUser" : 0,
      "inputAbbreviatedPath" : "\/img\/monster\/right-arm.png",
      "processed" : 1,
      "outputAbbreviatedPath" : "\/img\/monster\/right-arm.png",
      "initialSize" : 2470,
      "fileType" : 8192
    },
    "\/less\/includes\/bootstrap\/popovers.less" : {
      "ieCompatibility" : 1,
      "inputAbbreviatedPath" : "\/less\/includes\/bootstrap\/popovers.less",
      "outputAbbreviatedPath" : "\/less\/includes\/css\/popovers.css",
      "outputPathIsSetByUser" : 0,
      "strictUnits" : 0,
      "relativeURLS" : 0,
      "ignore" : 1,
      "strictImports" : 0,
      "ignoreWasSetByUser" : 0,
      "shouldRunBless" : 0,
      "hidden" : 0,
      "strictMath" : 0,
      "outputStyle" : 0,
      "fileType" : 1,
      "debugStyle" : 0
    },
    "\/js\/modernizr.js" : {
      "ignoreWasSetByUser" : 0,
      "ignore" : 0,
      "hidden" : 0,
      "outputPathIsSetByUser" : 0,
      "inputAbbreviatedPath" : "\/js\/modernizr.js",
      "outputStyle" : 1,
      "syntaxCheckerStyle" : 0,
      "outputAbbreviatedPath" : "\/js\/modernizr-ck.js",
      "fileType" : 64
    },
    "\/less\/includes\/bootstrap\/carousel.less" : {
      "ieCompatibility" : 1,
      "inputAbbreviatedPath" : "\/less\/includes\/bootstrap\/carousel.less",
      "outputAbbreviatedPath" : "\/less\/includes\/css\/carousel.css",
      "outputPathIsSetByUser" : 0,
      "strictUnits" : 0,
      "relativeURLS" : 0,
      "ignore" : 1,
      "strictImports" : 0,
      "ignoreWasSetByUser" : 0,
      "shouldRunBless" : 0,
      "hidden" : 0,
      "strictMath" : 0,
      "outputStyle" : 0,
      "fileType" : 1,
      "debugStyle" : 0
    },
    "\/index.html" : {
      "ignoreWasSetByUser" : 0,
      "ignore" : 0,
      "hidden" : 0,
      "outputPathIsSetByUser" : 0,
      "inputAbbreviatedPath" : "\/index.html",
      "outputAbbreviatedPath" : "No Output Path",
      "fileType" : 2048
    },
    "\/js\/app.js" : {
      "ignoreWasSetByUser" : 1,
      "ignore" : 1,
      "hidden" : 0,
      "outputPathIsSetByUser" : 0,
      "inputAbbreviatedPath" : "\/js\/app.js",
      "outputStyle" : 1,
      "syntaxCheckerStyle" : 1,
      "outputAbbreviatedPath" : "\/js\/app-ck.js",
      "fileType" : 64
    },
    "\/less\/includes\/bootstrap\/forms.less" : {
      "ieCompatibility" : 1,
      "inputAbbreviatedPath" : "\/less\/includes\/bootstrap\/forms.less",
      "outputAbbreviatedPath" : "\/less\/includes\/css\/forms.css",
      "outputPathIsSetByUser" : 0,
      "strictUnits" : 0,
      "relativeURLS" : 0,
      "ignore" : 1,
      "strictImports" : 0,
      "ignoreWasSetByUser" : 0,
      "shouldRunBless" : 0,
      "hidden" : 0,
      "strictMath" : 0,
      "outputStyle" : 0,
      "fileType" : 1,
      "debugStyle" : 0
    },
    "\/less\/includes\/bootstrap\/buttons.less" : {
      "ieCompatibility" : 1,
      "inputAbbreviatedPath" : "\/less\/includes\/bootstrap\/buttons.less",
      "outputAbbreviatedPath" : "\/less\/includes\/css\/buttons.css",
      "outputPathIsSetByUser" : 0,
      "strictUnits" : 0,
      "relativeURLS" : 0,
      "ignore" : 1,
      "strictImports" : 0,
      "ignoreWasSetByUser" : 0,
      "shouldRunBless" : 0,
      "hidden" : 0,
      "strictMath" : 0,
      "outputStyle" : 0,
      "fileType" : 1,
      "debugStyle" : 0
    },
    "\/less\/includes\/bootstrap\/tests\/css-tests.css" : {
      "ignoreWasSetByUser" : 0,
      "ignore" : 0,
      "hidden" : 0,
      "outputPathIsSetByUser" : 0,
      "inputAbbreviatedPath" : "\/less\/includes\/bootstrap\/tests\/css-tests.css",
      "outputAbbreviatedPath" : "No Output Path",
      "fileType" : 16
    },
    "\/less\/includes\/bootstrap\/responsive-1200px-min.less" : {
      "ieCompatibility" : 1,
      "inputAbbreviatedPath" : "\/less\/includes\/bootstrap\/responsive-1200px-min.less",
      "outputAbbreviatedPath" : "\/less\/includes\/css\/responsive-1200px-min.css",
      "outputPathIsSetByUser" : 0,
      "strictUnits" : 0,
      "relativeURLS" : 0,
      "ignore" : 1,
      "strictImports" : 0,
      "ignoreWasSetByUser" : 0,
      "shouldRunBless" : 0,
      "hidden" : 0,
      "strictMath" : 0,
      "outputStyle" : 0,
      "fileType" : 1,
      "debugStyle" : 0
    },
    "\/css\/site.css" : {
      "ignoreWasSetByUser" : 0,
      "ignore" : 1,
      "hidden" : 0,
      "outputPathIsSetByUser" : 0,
      "inputAbbreviatedPath" : "\/css\/site.css",
      "outputAbbreviatedPath" : "\/No Output Path",
      "fileType" : 16
    },
    "\/less\/includes\/bootstrap\/responsive-768px-979px.less" : {
      "ieCompatibility" : 1,
      "inputAbbreviatedPath" : "\/less\/includes\/bootstrap\/responsive-768px-979px.less",
      "outputAbbreviatedPath" : "\/less\/includes\/css\/responsive-768px-979px.css",
      "outputPathIsSetByUser" : 0,
      "strictUnits" : 0,
      "relativeURLS" : 0,
      "ignore" : 1,
      "strictImports" : 0,
      "ignoreWasSetByUser" : 0,
      "shouldRunBless" : 0,
      "hidden" : 0,
      "strictMath" : 0,
      "outputStyle" : 0,
      "fileType" : 1,
      "debugStyle" : 0
    },
    "\/less\/includes\/bootstrap\/grid.less" : {
      "ieCompatibility" : 1,
      "inputAbbreviatedPath" : "\/less\/includes\/bootstrap\/grid.less",
      "outputAbbreviatedPath" : "\/less\/includes\/css\/grid.css",
      "outputPathIsSetByUser" : 0,
      "strictUnits" : 0,
      "relativeURLS" : 0,
      "ignore" : 1,
      "strictImports" : 0,
      "ignoreWasSetByUser" : 0,
      "shouldRunBless" : 0,
      "hidden" : 0,
      "strictMath" : 0,
      "outputStyle" : 0,
      "fileType" : 1,
      "debugStyle" : 0
    },
    "\/less\/includes\/bootstrap\/code.less" : {
      "ieCompatibility" : 1,
      "inputAbbreviatedPath" : "\/less\/includes\/bootstrap\/code.less",
      "outputAbbreviatedPath" : "\/less\/includes\/css\/code.css",
      "outputPathIsSetByUser" : 0,
      "strictUnits" : 0,
      "relativeURLS" : 0,
      "ignore" : 1,
      "strictImports" : 0,
      "ignoreWasSetByUser" : 0,
      "shouldRunBless" : 0,
      "hidden" : 0,
      "strictMath" : 0,
      "outputStyle" : 0,
      "fileType" : 1,
      "debugStyle" : 0
    },
    "\/less\/includes\/bootstrap\/responsive-utilities.less" : {
      "ieCompatibility" : 1,
      "inputAbbreviatedPath" : "\/less\/includes\/bootstrap\/responsive-utilities.less",
      "outputAbbreviatedPath" : "\/less\/includes\/css\/responsive-utilities.css",
      "outputPathIsSetByUser" : 0,
      "strictUnits" : 0,
      "relativeURLS" : 0,
      "ignore" : 1,
      "strictImports" : 0,
      "ignoreWasSetByUser" : 0,
      "shouldRunBless" : 0,
      "hidden" : 0,
      "strictMath" : 0,
      "outputStyle" : 0,
      "fileType" : 1,
      "debugStyle" : 0
    },
    "\/less\/includes\/bootstrap\/hero-unit.less" : {
      "ieCompatibility" : 1,
      "inputAbbreviatedPath" : "\/less\/includes\/bootstrap\/hero-unit.less",
      "outputAbbreviatedPath" : "\/less\/includes\/css\/hero-unit.css",
      "outputPathIsSetByUser" : 0,
      "strictUnits" : 0,
      "relativeURLS" : 0,
      "ignore" : 1,
      "strictImports" : 0,
      "ignoreWasSetByUser" : 0,
      "shouldRunBless" : 0,
      "hidden" : 0,
      "strictMath" : 0,
      "outputStyle" : 0,
      "fileType" : 1,
      "debugStyle" : 0
    },
    "\/less\/includes\/bootstrap\/progress-bars.less" : {
      "ieCompatibility" : 1,
      "inputAbbreviatedPath" : "\/less\/includes\/bootstrap\/progress-bars.less",
      "outputAbbreviatedPath" : "\/less\/includes\/css\/progress-bars.css",
      "outputPathIsSetByUser" : 0,
      "strictUnits" : 0,
      "relativeURLS" : 0,
      "ignore" : 1,
      "strictImports" : 0,
      "ignoreWasSetByUser" : 0,
      "shouldRunBless" : 0,
      "hidden" : 0,
      "strictMath" : 0,
      "outputStyle" : 0,
      "fileType" : 1,
      "debugStyle" : 0
    },
    "\/less\/includes\/character.less" : {
      "ieCompatibility" : 1,
      "inputAbbreviatedPath" : "\/less\/includes\/character.less",
      "outputAbbreviatedPath" : "\/less\/css\/character.css",
      "outputPathIsSetByUser" : 0,
      "strictUnits" : 0,
      "relativeURLS" : 0,
      "ignore" : 1,
      "strictImports" : 0,
      "ignoreWasSetByUser" : 0,
      "shouldRunBless" : 0,
      "hidden" : 0,
      "strictMath" : 0,
      "outputStyle" : 0,
      "fileType" : 1,
      "debugStyle" : 0
    },
    "\/img\/monster\/left-arm.png" : {
      "ignoreWasSetByUser" : 0,
      "ignore" : 0,
      "hidden" : 0,
      "outputPathIsSetByUser" : 0,
      "inputAbbreviatedPath" : "\/img\/monster\/left-arm.png",
      "processed" : 1,
      "outputAbbreviatedPath" : "\/img\/monster\/left-arm.png",
      "initialSize" : 2688,
      "fileType" : 8192
    },
    "\/less\/includes\/bootstrap\/breadcrumbs.less" : {
      "ieCompatibility" : 1,
      "inputAbbreviatedPath" : "\/less\/includes\/bootstrap\/breadcrumbs.less",
      "outputAbbreviatedPath" : "\/less\/includes\/css\/breadcrumbs.css",
      "outputPathIsSetByUser" : 0,
      "strictUnits" : 0,
      "relativeURLS" : 0,
      "ignore" : 1,
      "strictImports" : 0,
      "ignoreWasSetByUser" : 0,
      "shouldRunBless" : 0,
      "hidden" : 0,
      "strictMath" : 0,
      "outputStyle" : 0,
      "fileType" : 1,
      "debugStyle" : 0
    },
    "\/less\/includes\/bootstrap\/close.less" : {
      "ieCompatibility" : 1,
      "inputAbbreviatedPath" : "\/less\/includes\/bootstrap\/close.less",
      "outputAbbreviatedPath" : "\/less\/includes\/css\/close.css",
      "outputPathIsSetByUser" : 0,
      "strictUnits" : 0,
      "relativeURLS" : 0,
      "ignore" : 1,
      "strictImports" : 0,
      "ignoreWasSetByUser" : 0,
      "shouldRunBless" : 0,
      "hidden" : 0,
      "strictMath" : 0,
      "outputStyle" : 0,
      "fileType" : 1,
      "debugStyle" : 0
    },
    "\/less\/includes\/bootstrap\/tests\/navbar-static-top.html" : {
      "ignoreWasSetByUser" : 0,
      "ignore" : 0,
      "hidden" : 0,
      "outputPathIsSetByUser" : 0,
      "inputAbbreviatedPath" : "\/less\/includes\/bootstrap\/tests\/navbar-static-top.html",
      "outputAbbreviatedPath" : "No Output Path",
      "fileType" : 2048
    },
    "\/less\/includes\/bootstrap\/type.less" : {
      "ieCompatibility" : 1,
      "inputAbbreviatedPath" : "\/less\/includes\/bootstrap\/type.less",
      "outputAbbreviatedPath" : "\/less\/includes\/css\/type.css",
      "outputPathIsSetByUser" : 0,
      "strictUnits" : 0,
      "relativeURLS" : 0,
      "ignore" : 1,
      "strictImports" : 0,
      "ignoreWasSetByUser" : 0,
      "shouldRunBless" : 0,
      "hidden" : 0,
      "strictMath" : 0,
      "outputStyle" : 0,
      "fileType" : 1,
      "debugStyle" : 0
    },
    "\/less\/includes\/bootstrap\/reset.less" : {
      "ieCompatibility" : 1,
      "inputAbbreviatedPath" : "\/less\/includes\/bootstrap\/reset.less",
      "outputAbbreviatedPath" : "\/less\/includes\/css\/reset.css",
      "outputPathIsSetByUser" : 0,
      "strictUnits" : 0,
      "relativeURLS" : 0,
      "ignore" : 1,
      "strictImports" : 0,
      "ignoreWasSetByUser" : 0,
      "shouldRunBless" : 0,
      "hidden" : 0,
      "strictMath" : 0,
      "outputStyle" : 0,
      "fileType" : 1,
      "debugStyle" : 0
    },
    "\/less\/includes\/bootstrap\/modals.less" : {
      "ieCompatibility" : 1,
      "inputAbbreviatedPath" : "\/less\/includes\/bootstrap\/modals.less",
      "outputAbbreviatedPath" : "\/less\/includes\/css\/modals.css",
      "outputPathIsSetByUser" : 0,
      "strictUnits" : 0,
      "relativeURLS" : 0,
      "ignore" : 1,
      "strictImports" : 0,
      "ignoreWasSetByUser" : 0,
      "shouldRunBless" : 0,
      "hidden" : 0,
      "strictMath" : 0,
      "outputStyle" : 0,
      "fileType" : 1,
      "debugStyle" : 0
    },
    "\/less\/includes\/bootstrap\/responsive.less" : {
      "ieCompatibility" : 1,
      "inputAbbreviatedPath" : "\/less\/includes\/bootstrap\/responsive.less",
      "outputAbbreviatedPath" : "\/less\/includes\/css\/responsive.css",
      "outputPathIsSetByUser" : 0,
      "strictUnits" : 0,
      "relativeURLS" : 0,
      "ignore" : 1,
      "strictImports" : 0,
      "ignoreWasSetByUser" : 1,
      "shouldRunBless" : 0,
      "hidden" : 0,
      "strictMath" : 0,
      "outputStyle" : 0,
      "fileType" : 1,
      "debugStyle" : 0
    },
    "\/js\/modernizr-ck.js" : {
      "ignoreWasSetByUser" : 0,
      "ignore" : 1,
      "hidden" : 0,
      "outputPathIsSetByUser" : 0,
      "inputAbbreviatedPath" : "\/js\/modernizr-ck.js",
      "outputStyle" : 1,
      "syntaxCheckerStyle" : 1,
      "outputAbbreviatedPath" : "\/js\/modernizr-ck-ck.js",
      "fileType" : 64
    },
    "\/less\/includes\/bootstrap\/navbar.less" : {
      "ieCompatibility" : 1,
      "inputAbbreviatedPath" : "\/less\/includes\/bootstrap\/navbar.less",
      "outputAbbreviatedPath" : "\/less\/includes\/css\/navbar.css",
      "outputPathIsSetByUser" : 0,
      "strictUnits" : 0,
      "relativeURLS" : 0,
      "ignore" : 1,
      "strictImports" : 0,
      "ignoreWasSetByUser" : 0,
      "shouldRunBless" : 0,
      "hidden" : 0,
      "strictMath" : 0,
      "outputStyle" : 0,
      "fileType" : 1,
      "debugStyle" : 0
    },
    "\/less\/includes\/bootstrap\/dropdowns.less" : {
      "ieCompatibility" : 1,
      "inputAbbreviatedPath" : "\/less\/includes\/bootstrap\/dropdowns.less",
      "outputAbbreviatedPath" : "\/less\/includes\/css\/dropdowns.css",
      "outputPathIsSetByUser" : 0,
      "strictUnits" : 0,
      "relativeURLS" : 0,
      "ignore" : 1,
      "strictImports" : 0,
      "ignoreWasSetByUser" : 0,
      "shouldRunBless" : 0,
      "hidden" : 0,
      "strictMath" : 0,
      "outputStyle" : 0,
      "fileType" : 1,
      "debugStyle" : 0
    },
    "\/less\/includes\/bootstrap\/tests\/forms-responsive.html" : {
      "ignoreWasSetByUser" : 0,
      "ignore" : 0,
      "hidden" : 0,
      "outputPathIsSetByUser" : 0,
      "inputAbbreviatedPath" : "\/less\/includes\/bootstrap\/tests\/forms-responsive.html",
      "outputAbbreviatedPath" : "No Output Path",
      "fileType" : 2048
    },
    "\/img\/glyphicons-halflings-white.png" : {
      "ignoreWasSetByUser" : 0,
      "ignore" : 0,
      "hidden" : 0,
      "outputPathIsSetByUser" : 0,
      "inputAbbreviatedPath" : "\/img\/glyphicons-halflings-white.png",
      "processed" : 1,
      "outputAbbreviatedPath" : "\/img\/glyphicons-halflings-white.png",
      "initialSize" : 8777,
      "fileType" : 8192
    },
    "\/less\/includes\/bootstrap\/media.less" : {
      "ieCompatibility" : 1,
      "inputAbbreviatedPath" : "\/less\/includes\/bootstrap\/media.less",
      "outputAbbreviatedPath" : "\/less\/includes\/css\/media.css",
      "outputPathIsSetByUser" : 0,
      "strictUnits" : 0,
      "relativeURLS" : 0,
      "ignore" : 1,
      "strictImports" : 0,
      "ignoreWasSetByUser" : 0,
      "shouldRunBless" : 0,
      "hidden" : 0,
      "strictMath" : 0,
      "outputStyle" : 0,
      "fileType" : 1,
      "debugStyle" : 0
    },
    "\/less\/includes\/bootstrap\/thumbnails.less" : {
      "ieCompatibility" : 1,
      "inputAbbreviatedPath" : "\/less\/includes\/bootstrap\/thumbnails.less",
      "outputAbbreviatedPath" : "\/less\/includes\/css\/thumbnails.css",
      "outputPathIsSetByUser" : 0,
      "strictUnits" : 0,
      "relativeURLS" : 0,
      "ignore" : 1,
      "strictImports" : 0,
      "ignoreWasSetByUser" : 0,
      "shouldRunBless" : 0,
      "hidden" : 0,
      "strictMath" : 0,
      "outputStyle" : 0,
      "fileType" : 1,
      "debugStyle" : 0
    },
    "\/less\/includes\/bootstrap\/tables.less" : {
      "ieCompatibility" : 1,
      "inputAbbreviatedPath" : "\/less\/includes\/bootstrap\/tables.less",
      "outputAbbreviatedPath" : "\/less\/includes\/css\/tables.css",
      "outputPathIsSetByUser" : 0,
      "strictUnits" : 0,
      "relativeURLS" : 0,
      "ignore" : 1,
      "strictImports" : 0,
      "ignoreWasSetByUser" : 0,
      "shouldRunBless" : 0,
      "hidden" : 0,
      "strictMath" : 0,
      "outputStyle" : 0,
      "fileType" : 1,
      "debugStyle" : 0
    },
    "\/less\/includes\/bootstrap\/pager.less" : {
      "ieCompatibility" : 1,
      "inputAbbreviatedPath" : "\/less\/includes\/bootstrap\/pager.less",
      "outputAbbreviatedPath" : "\/less\/includes\/css\/pager.css",
      "outputPathIsSetByUser" : 0,
      "strictUnits" : 0,
      "relativeURLS" : 0,
      "ignore" : 1,
      "strictImports" : 0,
      "ignoreWasSetByUser" : 0,
      "shouldRunBless" : 0,
      "hidden" : 0,
      "strictMath" : 0,
      "outputStyle" : 0,
      "fileType" : 1,
      "debugStyle" : 0
    },
    "\/less\/includes\/bootstrap\/labels-badges.less" : {
      "ieCompatibility" : 1,
      "inputAbbreviatedPath" : "\/less\/includes\/bootstrap\/labels-badges.less",
      "outputAbbreviatedPath" : "\/less\/includes\/css\/labels-badges.css",
      "outputPathIsSetByUser" : 0,
      "strictUnits" : 0,
      "relativeURLS" : 0,
      "ignore" : 1,
      "strictImports" : 0,
      "ignoreWasSetByUser" : 0,
      "shouldRunBless" : 0,
      "hidden" : 0,
      "strictMath" : 0,
      "outputStyle" : 0,
      "fileType" : 1,
      "debugStyle" : 0
    },
    "\/less\/includes\/bootstrap\/navs.less" : {
      "ieCompatibility" : 1,
      "inputAbbreviatedPath" : "\/less\/includes\/bootstrap\/navs.less",
      "outputAbbreviatedPath" : "\/less\/includes\/css\/navs.css",
      "outputPathIsSetByUser" : 0,
      "strictUnits" : 0,
      "relativeURLS" : 0,
      "ignore" : 1,
      "strictImports" : 0,
      "ignoreWasSetByUser" : 0,
      "shouldRunBless" : 0,
      "hidden" : 0,
      "strictMath" : 0,
      "outputStyle" : 0,
      "fileType" : 1,
      "debugStyle" : 0
    },
    "\/img\/grey.png" : {
      "ignoreWasSetByUser" : 0,
      "ignore" : 0,
      "hidden" : 0,
      "outputPathIsSetByUser" : 0,
      "inputAbbreviatedPath" : "\/img\/grey.png",
      "processed" : 1,
      "outputAbbreviatedPath" : "\/img\/grey.png",
      "initialSize" : 45541,
      "fileType" : 8192
    },
    "\/less\/includes\/bootstrap\/mixins.less" : {
      "ieCompatibility" : 1,
      "inputAbbreviatedPath" : "\/less\/includes\/bootstrap\/mixins.less",
      "outputAbbreviatedPath" : "\/less\/includes\/css\/mixins.css",
      "outputPathIsSetByUser" : 0,
      "strictUnits" : 0,
      "relativeURLS" : 0,
      "ignore" : 1,
      "strictImports" : 0,
      "ignoreWasSetByUser" : 0,
      "shouldRunBless" : 0,
      "hidden" : 0,
      "strictMath" : 0,
      "outputStyle" : 0,
      "fileType" : 1,
      "debugStyle" : 0
    },
    "\/img\/paper_top.png" : {
      "ignoreWasSetByUser" : 0,
      "ignore" : 0,
      "hidden" : 0,
      "outputPathIsSetByUser" : 0,
      "inputAbbreviatedPath" : "\/img\/paper_top.png",
      "processed" : 1,
      "outputAbbreviatedPath" : "\/img\/paper_top.png",
      "initialSize" : 7328,
      "fileType" : 8192
    },
    "\/less\/includes\/bootstrap\/utilities.less" : {
      "ieCompatibility" : 1,
      "inputAbbreviatedPath" : "\/less\/includes\/bootstrap\/utilities.less",
      "outputAbbreviatedPath" : "\/less\/includes\/css\/utilities.css",
      "outputPathIsSetByUser" : 0,
      "strictUnits" : 0,
      "relativeURLS" : 0,
      "ignore" : 1,
      "strictImports" : 0,
      "ignoreWasSetByUser" : 0,
      "shouldRunBless" : 0,
      "hidden" : 0,
      "strictMath" : 0,
      "outputStyle" : 0,
      "fileType" : 1,
      "debugStyle" : 0
    },
    "\/less\/includes\/bootstrap\/layouts.less" : {
      "ieCompatibility" : 1,
      "inputAbbreviatedPath" : "\/less\/includes\/bootstrap\/layouts.less",
      "outputAbbreviatedPath" : "\/less\/includes\/css\/layouts.css",
      "outputPathIsSetByUser" : 0,
      "strictUnits" : 0,
      "relativeURLS" : 0,
      "ignore" : 1,
      "strictImports" : 0,
      "ignoreWasSetByUser" : 0,
      "shouldRunBless" : 0,
      "hidden" : 0,
      "strictMath" : 0,
      "outputStyle" : 0,
      "fileType" : 1,
      "debugStyle" : 0
    },
    "\/less\/includes\/signika.less" : {
      "ieCompatibility" : 1,
      "inputAbbreviatedPath" : "\/less\/includes\/signika.less",
      "outputAbbreviatedPath" : "\/less\/css\/signika.css",
      "outputPathIsSetByUser" : 0,
      "strictUnits" : 0,
      "relativeURLS" : 0,
      "ignore" : 1,
      "strictImports" : 0,
      "ignoreWasSetByUser" : 1,
      "shouldRunBless" : 0,
      "hidden" : 0,
      "strictMath" : 0,
      "outputStyle" : 0,
      "fileType" : 1,
      "debugStyle" : 0
    },
    "\/js\/bootstrap.js" : {
      "ignoreWasSetByUser" : 0,
      "ignore" : 0,
      "hidden" : 0,
      "outputPathIsSetByUser" : 0,
      "inputAbbreviatedPath" : "\/js\/bootstrap.js",
      "outputStyle" : 1,
      "syntaxCheckerStyle" : 0,
      "outputAbbreviatedPath" : "\/js\/bootstrap-ck.js",
      "fileType" : 64
    },
    "\/less\/includes\/font-awesome.less" : {
      "ieCompatibility" : 1,
      "inputAbbreviatedPath" : "\/less\/includes\/font-awesome.less",
      "outputAbbreviatedPath" : "\/less\/css\/font-awesome.css",
      "outputPathIsSetByUser" : 0,
      "strictUnits" : 0,
      "relativeURLS" : 0,
      "ignore" : 1,
      "strictImports" : 0,
      "ignoreWasSetByUser" : 1,
      "shouldRunBless" : 0,
      "hidden" : 0,
      "strictMath" : 0,
      "outputStyle" : 0,
      "fileType" : 1,
      "debugStyle" : 0
    },
    "\/less\/includes\/bootstrap\/tests\/navbar-fixed-top.html" : {
      "ignoreWasSetByUser" : 0,
      "ignore" : 0,
      "hidden" : 0,
      "outputPathIsSetByUser" : 0,
      "inputAbbreviatedPath" : "\/less\/includes\/bootstrap\/tests\/navbar-fixed-top.html",
      "outputAbbreviatedPath" : "No Output Path",
      "fileType" : 2048
    },
    "\/less\/includes\/bootstrap\/sprites.less" : {
      "ieCompatibility" : 1,
      "inputAbbreviatedPath" : "\/less\/includes\/bootstrap\/sprites.less",
      "outputAbbreviatedPath" : "\/less\/includes\/css\/sprites.css",
      "outputPathIsSetByUser" : 0,
      "strictUnits" : 0,
      "relativeURLS" : 0,
      "ignore" : 1,
      "strictImports" : 0,
      "ignoreWasSetByUser" : 0,
      "shouldRunBless" : 0,
      "hidden" : 0,
      "strictMath" : 0,
      "outputStyle" : 0,
      "fileType" : 1,
      "debugStyle" : 0
    },
    "\/img\/paper_bottom.png" : {
      "ignoreWasSetByUser" : 0,
      "ignore" : 0,
      "hidden" : 0,
      "outputPathIsSetByUser" : 0,
      "inputAbbreviatedPath" : "\/img\/paper_bottom.png",
      "processed" : 1,
      "outputAbbreviatedPath" : "\/img\/paper_bottom.png",
      "initialSize" : 6470,
      "fileType" : 8192
    },
    "\/less\/includes\/bootstrap\/scaffolding.less" : {
      "ieCompatibility" : 1,
      "inputAbbreviatedPath" : "\/less\/includes\/bootstrap\/scaffolding.less",
      "outputAbbreviatedPath" : "\/less\/includes\/css\/scaffolding.css",
      "outputPathIsSetByUser" : 0,
      "strictUnits" : 0,
      "relativeURLS" : 0,
      "ignore" : 1,
      "strictImports" : 0,
      "ignoreWasSetByUser" : 0,
      "shouldRunBless" : 0,
      "hidden" : 0,
      "strictMath" : 0,
      "outputStyle" : 0,
      "fileType" : 1,
      "debugStyle" : 0
    },
    "\/img\/grey2.png" : {
      "ignoreWasSetByUser" : 0,
      "ignore" : 0,
      "hidden" : 0,
      "outputPathIsSetByUser" : 0,
      "inputAbbreviatedPath" : "\/img\/grey2.png",
      "processed" : 1,
      "outputAbbreviatedPath" : "\/img\/grey2.png",
      "initialSize" : 54960,
      "fileType" : 8192
    },
    "\/less\/includes\/bootstrap\/pagination.less" : {
      "ieCompatibility" : 1,
      "inputAbbreviatedPath" : "\/less\/includes\/bootstrap\/pagination.less",
      "outputAbbreviatedPath" : "\/less\/includes\/css\/pagination.css",
      "outputPathIsSetByUser" : 0,
      "strictUnits" : 0,
      "relativeURLS" : 0,
      "ignore" : 1,
      "strictImports" : 0,
      "ignoreWasSetByUser" : 0,
      "shouldRunBless" : 0,
      "hidden" : 0,
      "strictMath" : 0,
      "outputStyle" : 0,
      "fileType" : 1,
      "debugStyle" : 0
    },
    "\/less\/includes\/bootstrap\/tests\/navbar.html" : {
      "ignoreWasSetByUser" : 0,
      "ignore" : 0,
      "hidden" : 0,
      "outputPathIsSetByUser" : 0,
      "inputAbbreviatedPath" : "\/less\/includes\/bootstrap\/tests\/navbar.html",
      "outputAbbreviatedPath" : "No Output Path",
      "fileType" : 2048
    },
    "\/less\/includes\/bootstrap\/variables.less" : {
      "ieCompatibility" : 1,
      "inputAbbreviatedPath" : "\/less\/includes\/bootstrap\/variables.less",
      "outputAbbreviatedPath" : "\/less\/includes\/css\/variables.css",
      "outputPathIsSetByUser" : 0,
      "strictUnits" : 0,
      "relativeURLS" : 0,
      "ignore" : 1,
      "strictImports" : 0,
      "ignoreWasSetByUser" : 0,
      "shouldRunBless" : 0,
      "hidden" : 0,
      "strictMath" : 0,
      "outputStyle" : 0,
      "fileType" : 1,
      "debugStyle" : 0
    },
    "\/js\/bootstrap-ck.js" : {
      "ignoreWasSetByUser" : 0,
      "ignore" : 1,
      "hidden" : 0,
      "outputPathIsSetByUser" : 0,
      "inputAbbreviatedPath" : "\/js\/bootstrap-ck.js",
      "outputStyle" : 1,
      "syntaxCheckerStyle" : 1,
      "outputAbbreviatedPath" : "\/js\/bootstrap-ck-ck.js",
      "fileType" : 64
    },
    "\/less\/includes\/bootstrap\/tests\/buttons.html" : {
      "ignoreWasSetByUser" : 0,
      "ignore" : 0,
      "hidden" : 0,
      "outputPathIsSetByUser" : 0,
      "inputAbbreviatedPath" : "\/less\/includes\/bootstrap\/tests\/buttons.html",
      "outputAbbreviatedPath" : "No Output Path",
      "fileType" : 2048
    },
    "\/less\/includes\/bootstrap\/responsive-767px-max.less" : {
      "ieCompatibility" : 1,
      "inputAbbreviatedPath" : "\/less\/includes\/bootstrap\/responsive-767px-max.less",
      "outputAbbreviatedPath" : "\/less\/includes\/css\/responsive-767px-max.css",
      "outputPathIsSetByUser" : 0,
      "strictUnits" : 0,
      "relativeURLS" : 0,
      "ignore" : 1,
      "strictImports" : 0,
      "ignoreWasSetByUser" : 0,
      "shouldRunBless" : 0,
      "hidden" : 0,
      "strictMath" : 0,
      "outputStyle" : 0,
      "fileType" : 1,
      "debugStyle" : 0
    },
    "\/img\/paper_slice.png" : {
      "ignoreWasSetByUser" : 0,
      "ignore" : 0,
      "hidden" : 0,
      "outputPathIsSetByUser" : 0,
      "inputAbbreviatedPath" : "\/img\/paper_slice.png",
      "processed" : 1,
      "outputAbbreviatedPath" : "\/img\/paper_slice.png",
      "initialSize" : 981,
      "fileType" : 8192
    },
    "\/less\/site.less" : {
      "ieCompatibility" : 1,
      "inputAbbreviatedPath" : "\/less\/site.less",
      "outputAbbreviatedPath" : "\/css\/site.css",
      "outputPathIsSetByUser" : 0,
      "strictUnits" : 0,
      "relativeURLS" : 0,
      "ignore" : 0,
      "strictImports" : 0,
      "ignoreWasSetByUser" : 1,
      "shouldRunBless" : 0,
      "hidden" : 0,
      "strictMath" : 0,
      "outputStyle" : 2,
      "fileType" : 1,
      "debugStyle" : 0
    },
    "\/less\/includes\/bootstrap\/button-groups.less" : {
      "ieCompatibility" : 1,
      "inputAbbreviatedPath" : "\/less\/includes\/bootstrap\/button-groups.less",
      "outputAbbreviatedPath" : "\/less\/includes\/css\/button-groups.css",
      "outputPathIsSetByUser" : 0,
      "strictUnits" : 0,
      "relativeURLS" : 0,
      "ignore" : 1,
      "strictImports" : 0,
      "ignoreWasSetByUser" : 0,
      "shouldRunBless" : 0,
      "hidden" : 0,
      "strictMath" : 0,
      "outputStyle" : 0,
      "fileType" : 1,
      "debugStyle" : 0
    },
    "\/img\/glyphicons-halflings.png" : {
      "ignoreWasSetByUser" : 0,
      "ignore" : 0,
      "hidden" : 0,
      "outputPathIsSetByUser" : 0,
      "inputAbbreviatedPath" : "\/img\/glyphicons-halflings.png",
      "processed" : 1,
      "outputAbbreviatedPath" : "\/img\/glyphicons-halflings.png",
      "initialSize" : 12799,
      "fileType" : 8192
    },
    "\/less\/includes\/bootstrap\/wells.less" : {
      "ieCompatibility" : 1,
      "inputAbbreviatedPath" : "\/less\/includes\/bootstrap\/wells.less",
      "outputAbbreviatedPath" : "\/less\/includes\/css\/wells.css",
      "outputPathIsSetByUser" : 0,
      "strictUnits" : 0,
      "relativeURLS" : 0,
      "ignore" : 1,
      "strictImports" : 0,
      "ignoreWasSetByUser" : 0,
      "shouldRunBless" : 0,
      "hidden" : 0,
      "strictMath" : 0,
      "outputStyle" : 0,
      "fileType" : 1,
      "debugStyle" : 0
    },
    "\/less\/includes\/bootstrap\/tooltip.less" : {
      "ieCompatibility" : 1,
      "inputAbbreviatedPath" : "\/less\/includes\/bootstrap\/tooltip.less",
      "outputAbbreviatedPath" : "\/less\/includes\/css\/tooltip.css",
      "outputPathIsSetByUser" : 0,
      "strictUnits" : 0,
      "relativeURLS" : 0,
      "ignore" : 1,
      "strictImports" : 0,
      "ignoreWasSetByUser" : 0,
      "shouldRunBless" : 0,
      "hidden" : 0,
      "strictMath" : 0,
      "outputStyle" : 0,
      "fileType" : 1,
      "debugStyle" : 0
    },
    "\/img\/photos\/john.jpg" : {
      "ignoreWasSetByUser" : 0,
      "ignore" : 0,
      "hidden" : 0,
      "outputPathIsSetByUser" : 0,
      "inputAbbreviatedPath" : "\/img\/photos\/john.jpg",
      "processed" : 0,
      "outputAbbreviatedPath" : "\/img\/photos\/john.jpg",
      "initialSize" : 74913,
      "fileType" : 4096
    },
    "\/less\/includes\/bootstrap\/component-animations.less" : {
      "ieCompatibility" : 1,
      "inputAbbreviatedPath" : "\/less\/includes\/bootstrap\/component-animations.less",
      "outputAbbreviatedPath" : "\/less\/includes\/css\/component-animations.css",
      "outputPathIsSetByUser" : 0,
      "strictUnits" : 0,
      "relativeURLS" : 0,
      "ignore" : 1,
      "strictImports" : 0,
      "ignoreWasSetByUser" : 0,
      "shouldRunBless" : 0,
      "hidden" : 0,
      "strictMath" : 0,
      "outputStyle" : 0,
      "fileType" : 1,
      "debugStyle" : 0
    },
    "\/less\/includes\/font-awesome-ie7.less" : {
      "ieCompatibility" : 1,
      "inputAbbreviatedPath" : "\/less\/includes\/font-awesome-ie7.less",
      "outputAbbreviatedPath" : "\/less\/css\/font-awesome-ie7.css",
      "outputPathIsSetByUser" : 0,
      "strictUnits" : 0,
      "relativeURLS" : 0,
      "ignore" : 1,
      "strictImports" : 0,
      "ignoreWasSetByUser" : 1,
      "shouldRunBless" : 0,
      "hidden" : 0,
      "strictMath" : 0,
      "outputStyle" : 0,
      "fileType" : 1,
      "debugStyle" : 0
    },
    "\/less\/includes\/bootstrap\/bootstrap.less" : {
      "ieCompatibility" : 1,
      "inputAbbreviatedPath" : "\/less\/includes\/bootstrap\/bootstrap.less",
      "outputAbbreviatedPath" : "\/less\/includes\/css\/bootstrap.css",
      "outputPathIsSetByUser" : 0,
      "strictUnits" : 0,
      "relativeURLS" : 0,
      "ignore" : 1,
      "strictImports" : 0,
      "ignoreWasSetByUser" : 0,
      "shouldRunBless" : 0,
      "hidden" : 0,
      "strictMath" : 0,
      "outputStyle" : 0,
      "fileType" : 1,
      "debugStyle" : 0
    }
  },
  "manualImportLinks" : [

  ],
  "projectSettings" : {
    "hamlNoEscapeInAttributes" : 0,
    "kitAutoOutputPathStyle" : 0,
    "lessOutputStyle" : 0,
    "hamlAutoOutputPathReplace2" : "",
    "draggedImportConcatenationStyle" : 1,
    "jadeAutoOutputPathStyle" : 0,
    "hamlEscapeHTMLCharacters" : 0,
    "javascriptAutoOutputPathStyle" : 0,
    "hamlOutputFormat" : 2,
    "stylusAutoOutputPathReplace1" : "stylus",
    "lessStrictImports" : 0,
    "sassAutoOutputPathStyle" : 2,
    "stylusAutoOutputPathReplace2" : "css",
    "lessAutoOutputPathStyle" : 2,
    "lessIECompatibility" : 1,
    "genericWebpageFileExtensionsString" : "html, htm, shtml, shtm, xhtml, php, jsp, asp, aspx, erb, ctp",
    "lessStrictUnits" : 0,
    "lessStrictMath" : 0,
    "coffeeMinifyOutput" : 1,
    "javascriptOutputSuffix" : "-ck",
    "jadeOutputStyle" : 0,
    "coffeeAutoOutputPathStyle" : 0,
    "autoSyncProjectSettingsFile" : 1,
    "lessAutoOutputPathReplace1" : "less",
    "jadeAutoOutputPathReplace1" : "",
    "lessAutoOutputPathRelativePath" : "..\/css",
    "hamlAutoOutputPathRelativePath" : "",
    "jsCheckerReservedNamesString" : "",
    "javascriptOutputStyle" : 1,
    "stylusDebugStyle" : 0,
    "hamlUseCDATA" : 0,
    "hamlAutoOutputPathStyle" : 0,
    "sassDebugStyle" : 0,
    "hamlOutputStyle" : 0,
    "stylusAutoOutputPathRelativePath" : "..\/css",
    "jsCheckerIndent" : 4,
    "kitAutoOutputPathRelativePath" : "",
    "lessAutoOutputPathReplace2" : "css",
    "jadeAutoOutputPathReplace2" : "",
    "shouldRunBless" : 0,
    "stylusAutoOutputPathStyle" : 2,
    "coffeeCheckOutputStyle" : 0,
    "slimOutputStyle" : 1,
    "javascriptSyntaxCheckerStyle" : 1,
    "sassAutoOutputPathReplace1" : "sass",
    "slimAutoOutputPathReplace1" : "",
    "sassOutputStyle" : 0,
    "coffeeAutoOutputPathRelativePath" : "",
    "slimCompileOnly" : 0,
    "slimLogicless" : 0,
    "uglifyIndent" : 4,
    "jadeAutoOutputPathRelativePath" : "",
    "hamlUseUnixNewlines" : 0,
    "hamlAutoOutputPathReplace1" : "",
    "javascriptAutoOutputPathReplace1" : "",
    "stylusOutputStyle" : 0,
    "javascriptAutoOutputPathReplace2" : "",
    "sassAutoOutputPathRelativePath" : "..\/css",
    "coffeeAutoOutputPathReplace1" : "",
    "hamlUseDoubleQuotes" : 0,
    "coffeeAutoOutputPathReplace2" : "",
    "kitAutoOutputPathReplace1" : "",
    "uglifyReservedNamesString" : "",
    "coffeeOutputStyle" : 0,
    "slimAutoOutputPathRelativePath" : "",
    "jsHintFlags" : {
      "latedef" : 1,
      "newcap" : 1,
      "curly" : 1,
      "trailing" : 1,
      "nonew" : 1,
      "es3" : false,
      "freeze" : true,
      "yui" : 0,
      "mootools" : 0,
      "proto" : 0,
      "boss" : 0,
      "funcscope" : 0,
      "jquery" : 1,
      "esnext" : 0,
      "camelcase" : 0,
      "dojo" : 0,
      "strict" : 0,
      "devel" : 0,
      "wsh" : 0,
      "nonstandard" : 0,
      "asi" : 0,
      "moz" : false,
      "rhino" : 0,
      "smarttabs" : 0,
      "lastsemic" : 0,
      "noempty" : 0,
      "eqnull" : 0,
      "eqeqeq" : 1,
      "couch" : 0,
      "evil" : 0,
      "expr" : 0,
      "immed" : 0,
      "globalstrict" : 0,
      "undef" : 1,
      "iterator" : 0,
      "prototypejs" : 0,
      "noarg" : 1,
      "supernew" : 0,
      "node" : 0,
      "unused" : 1,
      "debug" : 0,
      "bitwise" : 1,
      "notypeof" : true,
      "white" : 0,
      "browser" : 1,
      "worker" : 0,
      "laxcomma" : 0,
      "multistr" : 0,
      "shadow" : 0,
      "sub" : 0,
      "plusplus" : 0,
      "scripturl" : 0,
      "forin" : 0,
      "loopfunc" : 0,
      "laxbreak" : 0
    },
    "jsLintFlags" : {
      "white" : 0,
      "unparam" : 0,
      "regexp" : 0,
      "nomen" : 0,
      "vars" : 0,
      "sub" : 0,
      "stupid" : 0,
      "continue" : false,
      "bitwise" : 0,
      "newcap" : 0,
      "sloppy" : 0,
      "closure" : false,
      "browser" : 1,
      "properties" : 0,
      "plusplus" : 0,
      "debug" : 0,
      "forin" : 0,
      "eqeq" : 0,
      "evil" : 0,
      "node" : 0,
      "rhino" : 0,
      "devel" : 0,
      "ass" : false
    },
    "uglifyFlags" : {
      "no-mangle-functions" : 0,
      "no-mangle" : 0,
      "no-copyright" : 0,
      "no-dead-code" : 0,
      "inline-script" : 0,
      "ascii" : 0,
      "unsafe" : 0,
      "mangle-toplevel" : 0,
      "no-seqs" : 1,
      "beautify" : 0,
      "lift-vars" : 0,
      "consolidate-primitive-values" : 0,
      "no-squeeze" : 0
    },
    "sassAutoOutputPathReplace2" : "css",
    "slimAutoOutputPathReplace2" : "",
    "jadeCompileDebug" : 1,
    "slimRailsCompatible" : 0,
    "kitAutoOutputPathReplace2" : "",
    "lessRelativeURLS" : 0,
    "lessDebugStyle" : 0,
    "javascriptAutoOutputPathRelativePath" : "",
    "slimAutoOutputPathStyle" : 0
  },
  "projectAttributes" : {
    "bourbonEnabled" : 0,
    "displayValue" : "Portfolio",
    "displayValueWasSetByUser" : 1,
    "compassEnabled" : 0
  }
}